{
   "series" : [
      {
         "name" : "Current Chain",
         "meta" : [
            "MANWAR",
            "PERLANCAR",
            "BKB",
            "LNATION",
            "ETHER",
            "RURBAN"
         ],
         "data" : [
            -826,
            -43,
            -4,
            -3,
            -3,
            -3
         ]
      },
      {
         "name" : "Longest Chain",
         "meta" : [
            "MANWAR",
            "BARBIE",
            "SKIM",
            "NEILB",
            "IVANWILLS",
            "KENTNL",
            "ETHER",
            "CSSON",
            "INGY",
            "RENEEB"
         ],
         "data" : [
            826,
            370,
            145,
            111,
            102,
            101,
            77,
            55,
            47,
            44
         ]
      }
   ],
   "subtitle" : {
      "text" : "Last updated at 2017-01-31 11:15:02 GMT"
   },
   "title" : {
      "text" : "CPAN Regulars Daily (Top 10)"
   }
}
