{
   "subtitle" : {
      "text" : "Last updated at 2021-01-04 22:00:05 GMT"
   },
   "series" : [
      {
         "name" : "Current Chain",
         "data" : [
            -599,
            -4,
            -4
         ],
         "meta" : [
            "PERLANCAR",
            "Perl6",
            "WYANT"
         ]
      },
      {
         "name" : "Longest Chain",
         "data" : [
            1027,
            599,
            370,
            145,
            111,
            102,
            101,
            77,
            76,
            55
         ],
         "meta" : [
            "MANWAR",
            "PERLANCAR",
            "BARBIE",
            "SKIM",
            "NEILB",
            "IVANWILLS",
            "KENTNL",
            "ETHER",
            "RENEEB",
            "CSSON"
         ]
      }
   ],
   "title" : {
      "text" : "CPAN Regulars Daily (Top 10)"
   }
}
