{
   "subtitle" : {
      "text" : "Last updated at 2019-08-04 08:00:02 GMT"
   },
   "series" : [
      {
         "meta" : [
            "MANWAR",
            "PERLANCAR",
            "SYBER",
            "BRAINBUZ"
         ],
         "name" : "Current Chain",
         "data" : [
            -92,
            -80,
            -5,
            -3
         ]
      },
      {
         "name" : "Longest Chain",
         "meta" : [
            "MANWAR",
            "BARBIE",
            "SKIM",
            "NEILB",
            "IVANWILLS",
            "KENTNL",
            "PERLANCAR",
            "ETHER",
            "RENEEB",
            "CSSON"
         ],
         "data" : [
            1027,
            370,
            145,
            111,
            102,
            101,
            81,
            77,
            76,
            55
         ]
      }
   ],
   "title" : {
      "text" : "CPAN Regulars Daily (Top 10)"
   }
}
