{
   "series" : [
      {
         "meta" : [
            "MANWAR",
            "RENEEB",
            "Perl6",
            "PLICEASE",
            "KRYDE",
            "PERLANCAR",
            "UTASHIRO",
            "KITANO"
         ],
         "data" : [
            -558,
            -61,
            -7,
            -4,
            -4,
            -4,
            -3,
            -3
         ],
         "name" : "Current Chain"
      },
      {
         "data" : [
            1027,
            370,
            145,
            111,
            102,
            101,
            81,
            77,
            61,
            55
         ],
         "name" : "Longest Chain",
         "meta" : [
            "MANWAR",
            "BARBIE",
            "SKIM",
            "NEILB",
            "IVANWILLS",
            "KENTNL",
            "PERLANCAR",
            "ETHER",
            "RENEEB",
            "CSSON"
         ]
      }
   ],
   "subtitle" : {
      "text" : "Last updated at 2019-03-01 23:00:02 GMT"
   },
   "title" : {
      "text" : "CPAN Regulars Daily (Top 10)"
   }
}
