{
   "series" : [
      {
         "name" : "Current Chain",
         "meta" : [
            "MANWAR",
            "VDB",
            "EXODIST",
            "ORKUN",
            "XSAWYERX",
            "PERLANCAR",
            "FELIPE"
         ],
         "data" : [
            -786,
            -5,
            -5,
            -5,
            -4,
            -3,
            -3
         ]
      },
      {
         "data" : [
            786,
            370,
            145,
            111,
            102,
            101,
            77,
            55,
            47,
            44
         ],
         "meta" : [
            "MANWAR",
            "BARBIE",
            "SKIM",
            "NEILB",
            "IVANWILLS",
            "KENTNL",
            "ETHER",
            "CSSON",
            "INGY",
            "RENEEB"
         ],
         "name" : "Longest Chain"
      }
   ],
   "title" : {
      "text" : "CPAN Regulars Daily (Top 10)"
   },
   "subtitle" : {
      "text" : "Last updated at 2016-12-22 11:00:01 GMT"
   }
}
