{
   "series" : [
      {
         "meta" : [
            "MANWAR",
            "ZENBAE",
            "MOOCOW"
         ],
         "name" : "Current Chain",
         "data" : [
            -619,
            -4,
            -3
         ]
      },
      {
         "data" : [
            619,
            370,
            145,
            111,
            102,
            101,
            77,
            55,
            47,
            44
         ],
         "name" : "Longest Chain",
         "meta" : [
            "MANWAR",
            "BARBIE",
            "SKIM",
            "NEILB",
            "IVANWILLS",
            "KENTNL",
            "ETHER",
            "CSSON",
            "INGY",
            "RENEEB"
         ]
      }
   ],
   "title" : {
      "text" : "CPAN Regulars Daily (Top 10)"
   },
   "subtitle" : {
      "text" : "Last updated at 2016-07-08 02:00:02 GMT"
   }
}
