{
   "title" : {
      "text" : "CPAN Regulars Daily (Top 10)"
   },
   "series" : [
      {
         "name" : "Current Chain",
         "meta" : [
            "MANWAR",
            "ETJ",
            "MLEHMANN"
         ],
         "data" : [
            -609,
            -3,
            -3
         ]
      },
      {
         "data" : [
            1027,
            370,
            145,
            111,
            102,
            101,
            81,
            77,
            76,
            55
         ],
         "meta" : [
            "MANWAR",
            "BARBIE",
            "SKIM",
            "NEILB",
            "IVANWILLS",
            "KENTNL",
            "PERLANCAR",
            "ETHER",
            "RENEEB",
            "CSSON"
         ],
         "name" : "Longest Chain"
      }
   ],
   "subtitle" : {
      "text" : "Last updated at 2019-04-21 16:00:03 GMT"
   }
}
