{
   "title" : {
      "text" : "CPAN Regulars Daily (Top 10)"
   },
   "series" : [
      {
         "name" : "Current Chain",
         "data" : [
            -266,
            -18,
            -9,
            -5,
            -5,
            -4,
            -3,
            -3
         ],
         "meta" : [
            "PERLANCAR",
            "Perl6",
            "FELIPE",
            "GUGOD",
            "PLICEASE",
            "MAMOD",
            "LEEJO",
            "BAREFOOT"
         ]
      },
      {
         "data" : [
            1027,
            370,
            266,
            145,
            111,
            102,
            101,
            77,
            76,
            55
         ],
         "meta" : [
            "MANWAR",
            "BARBIE",
            "PERLANCAR",
            "SKIM",
            "NEILB",
            "IVANWILLS",
            "KENTNL",
            "ETHER",
            "RENEEB",
            "CSSON"
         ],
         "name" : "Longest Chain"
      }
   ],
   "subtitle" : {
      "text" : "Last updated at 2020-02-06 06:00:02 GMT"
   }
}
