{
   "title" : {
      "text" : "CPAN Regulars Daily (Top 10)"
   },
   "series" : [
      {
         "data" : [
            -307,
            -4,
            -3,
            -3
         ],
         "meta" : [
            "PERLANCAR",
            "Perl6",
            "PLICEASE",
            "JMATES"
         ],
         "name" : "Current Chain"
      },
      {
         "name" : "Longest Chain",
         "meta" : [
            "MANWAR",
            "BARBIE",
            "PERLANCAR",
            "SKIM",
            "NEILB",
            "IVANWILLS",
            "KENTNL",
            "ETHER",
            "RENEEB",
            "CSSON"
         ],
         "data" : [
            1027,
            370,
            307,
            145,
            111,
            102,
            101,
            77,
            76,
            55
         ]
      }
   ],
   "subtitle" : {
      "text" : "Last updated at 2020-03-18 17:19:58 GMT"
   }
}
