{
   "title" : {
      "text" : "CPAN Regulars Daily (Top 10)"
   },
   "series" : [
      {
         "data" : [
            -114,
            -102,
            -5,
            -4,
            -3
         ],
         "name" : "Current Chain",
         "meta" : [
            "MANWAR",
            "PERLANCAR",
            "WYANT",
            "GENE",
            "SHLOMIF"
         ]
      },
      {
         "meta" : [
            "MANWAR",
            "BARBIE",
            "SKIM",
            "NEILB",
            "IVANWILLS",
            "PERLANCAR",
            "KENTNL",
            "ETHER",
            "RENEEB",
            "CSSON"
         ],
         "data" : [
            1027,
            370,
            145,
            111,
            102,
            102,
            101,
            77,
            76,
            55
         ],
         "name" : "Longest Chain"
      }
   ],
   "subtitle" : {
      "text" : "Last updated at 2019-08-26 20:00:02 GMT"
   }
}
