{
   "series" : [
      {
         "data" : [
            -138,
            -126,
            -3
         ],
         "meta" : [
            "MANWAR",
            "PERLANCAR",
            "UTASHIRO"
         ],
         "name" : "Current Chain"
      },
      {
         "meta" : [
            "MANWAR",
            "BARBIE",
            "SKIM",
            "PERLANCAR",
            "NEILB",
            "IVANWILLS",
            "KENTNL",
            "ETHER",
            "RENEEB",
            "CSSON"
         ],
         "name" : "Longest Chain",
         "data" : [
            1027,
            370,
            145,
            126,
            111,
            102,
            101,
            77,
            76,
            55
         ]
      }
   ],
   "subtitle" : {
      "text" : "Last updated at 2019-09-19 11:00:06 GMT"
   },
   "title" : {
      "text" : "CPAN Regulars Daily (Top 10)"
   }
}
