{
   "title" : {
      "text" : "CPAN Regulars Monthly (Top 10)"
   },
   "subtitle" : {
      "text" : "Last updated at 2024-12-04 20:13:26 GMT"
   },
   "series" : [
      {
         "meta" : [
            "BINGOS",
            "ETHER",
            "LEEJO",
            "PERLANCAR",
            "UTASHIRO",
            "OALDERS",
            "KIMOTO",
            "SKIM",
            "JDEGUEST",
            "DERF"
         ],
         "data" : [
            -225,
            -153,
            -128,
            -125,
            -78,
            -64,
            -37,
            -32,
            -31,
            -31
         ],
         "name" : "Current Chain"
      },
      {
         "data" : [
            245,
            225,
            153,
            146,
            142,
            133,
            128,
            125,
            120,
            114
         ],
         "name" : "Longest Chain",
         "meta" : [
            "DROLSKY",
            "BINGOS",
            "ETHER",
            "RJBS",
            "PEVANS",
            "PLICEASE",
            "LEEJO",
            "PERLANCAR",
            "SRI",
            "IVANWILLS"
         ]
      }
   ]
}
