{
   "subtitle" : {
      "text" : "Last updated at 2017-09-17 10:00:02 GMT"
   },
   "title" : {
      "text" : "NeoCPAN Uploaders Monthly (Top 20)"
   },
   "series" : [
      {
         "data" : [
            -44,
            -38,
            -4,
            -4,
            -4,
            -3,
            -3,
            -3,
            -3,
            -3,
            -3,
            -2,
            -2,
            -2,
            -2,
            -2,
            -2,
            -2,
            -2,
            -2
         ],
         "name" : "Current Chain",
         "meta" : [
            "MGV",
            "PERLANCAR",
            "PLICEASE",
            "ATHREEF",
            "DAVECROSS",
            "ZMUGHAL",
            "RENE",
            "DBOOK",
            "LNATION",
            "BPS",
            "JHTHORSEN",
            "FERREIRA",
            "AKALINUX",
            "PRBRENAN",
            "MANWAR",
            "WATERKIP",
            "Perl6",
            "SKIRMESS",
            "AMBA",
            "BKB"
         ]
      },
      {
         "meta" : [
            "KENTNL",
            "MGV",
            "PERLANCAR",
            "TOBYINK",
            "ETHER",
            "SHARYANTO",
            "TOKUHIROM",
            "BINGOS",
            "GUGOD",
            "NEILB",
            "FAYLAND",
            "RJBS",
            "RCLAMP",
            "MIYAGAWA",
            "MSCHWERN",
            "SKIM",
            "SIMON",
            "JHTHORSEN",
            "KAZEBURO",
            "INGY"
         ],
         "data" : [
            46,
            44,
            38,
            27,
            23,
            19,
            18,
            18,
            17,
            17,
            16,
            16,
            15,
            14,
            14,
            13,
            13,
            13,
            13,
            12
         ],
         "name" : "Longest Chain"
      }
   ]
}
