{
   "subtitle" : {
      "text" : "Last updated at 2016-03-02 10:00:02 GMT"
   },
   "title" : {
      "text" : "NeoCPAN Regulars Monthly (Top 50)"
   },
   "series" : [
      {
         "name" : "Current Chain",
         "data" : [
            -182,
            -120,
            -116,
            -91,
            -85,
            -77,
            -56,
            -48,
            -48,
            -44,
            -42,
            -42,
            -42,
            -38,
            -36,
            -35,
            -35,
            -33,
            -27,
            -27,
            -27,
            -26,
            -26,
            -24,
            -24,
            -23,
            -23,
            -23,
            -22,
            -21,
            -20,
            -20,
            -20,
            -19,
            -19,
            -18,
            -18,
            -17,
            -16,
            -15,
            -12,
            -12,
            -12,
            -12,
            -11,
            -11,
            -9,
            -9,
            -9,
            -9
         ],
         "meta" : [
            "DROLSKY",
            "BINGOS",
            "PEVANS",
            "DAGOLDEN",
            "TOKUHIROM",
            "LEONT",
            "SRI",
            "ETHER",
            "BOOK",
            "PLICEASE",
            "KENTNL",
            "YANICK",
            "FAYLAND",
            "AVENJ",
            "WYANT",
            "JHTHORSEN",
            "JJNAPIORK",
            "NEILB",
            "KUERBIS",
            "OLIVER",
            "JMATES",
            "ISHIGAKI",
            "MGV",
            "PJFL",
            "LEEJO",
            "REEDFISH",
            "IVANWILLS",
            "OALDERS",
            "BINARY",
            "MANWAR",
            "PERLANCAR",
            "SHLOMIF",
            "HORNBURG",
            "MIYAGAWA",
            "TANIGUCHI",
            "PREACTION",
            "SULLR",
            "SJDY",
            "DBOOK",
            "HOCHSTEN",
            "EXODIST",
            "AJPAGE",
            "KARUPA",
            "BENNING",
            "RURBAN",
            "KARMAN",
            "MELEZHIK",
            "STEVEB",
            "RSAVAGE",
            "BDFOY"
         ]
      },
      {
         "name" : "Longest Chain",
         "data" : [
            182,
            146,
            120,
            116,
            108,
            91,
            87,
            85,
            77,
            66,
            63,
            62,
            61,
            60,
            56,
            53,
            52,
            52,
            51,
            50,
            48,
            48,
            48,
            46,
            44,
            44,
            44,
            44,
            44,
            43,
            43,
            42,
            42,
            42,
            42,
            42,
            40,
            40,
            40,
            40,
            39,
            38,
            38,
            37,
            37,
            37,
            37,
            36,
            36,
            36
         ],
         "meta" : [
            "DROLSKY",
            "RJBS",
            "BINGOS",
            "PEVANS",
            "ADAMK",
            "DAGOLDEN",
            "KRYDE",
            "TOKUHIROM",
            "LEONT",
            "JKEGL",
            "MARKOV",
            "AUTRIJUS",
            "PETDANCE",
            "SHARYANTO",
            "SRI",
            "KWILLIAMS",
            "SALVA",
            "CJM",
            "SMUELLER",
            "FREW",
            "ETHER",
            "GFUJI",
            "BOOK",
            "DOY",
            "PLICEASE",
            "MLEHMANN",
            "AMBS",
            "RCLAMP",
            "SCHUBIGER",
            "FLORA",
            "FAYLAND",
            "KENTNL",
            "BARBIE",
            "KARMAN",
            "YANICK",
            "XSAWYERX",
            "LEOCHARRE",
            "MSERGEANT",
            "SHLOMIF",
            "LDS",
            "TOBYINK",
            "AVENJ",
            "SARTAK",
            "KAZEBURO",
            "VPIT",
            "HDIAS",
            "TANIGUCHI",
            "MIYAGAWA",
            "KIMOTO",
            "DMAKI"
         ]
      }
   ]
}
