{
   "subtitle" : {
      "text" : "Last updated at 2017-07-16 04:00:02 GMT"
   },
   "series" : [
      {
         "meta" : [
            "MGV",
            "PERLANCAR",
            "STEVEB",
            "CORION",
            "TOBYINK",
            "PLICEASE",
            "DCONWAY",
            "TEAM",
            "DBOOK",
            "DFARRELL",
            "JASEI",
            "NICS",
            "COFFEE",
            "DAVECROSS",
            "NEILB",
            "EXODIST",
            "REHSACK",
            "RORYRJB",
            "TTKCIAR",
            "WBRASWELL"
         ],
         "name" : "Current Chain",
         "data" : [
            -42,
            -36,
            -7,
            -3,
            -3,
            -2,
            -2,
            -2,
            -2,
            -2,
            -2,
            -2,
            -2,
            -2,
            -2,
            -2,
            -2,
            -2,
            -2,
            -2
         ]
      },
      {
         "name" : "Longest Chain",
         "meta" : [
            "KENTNL",
            "MGV",
            "PERLANCAR",
            "TOBYINK",
            "ETHER",
            "SHARYANTO",
            "TOKUHIROM",
            "BINGOS",
            "GUGOD",
            "NEILB",
            "FAYLAND",
            "RJBS",
            "RCLAMP",
            "MIYAGAWA",
            "MSCHWERN",
            "SKIM",
            "SIMON",
            "JHTHORSEN",
            "KAZEBURO",
            "INGY"
         ],
         "data" : [
            46,
            42,
            36,
            27,
            23,
            19,
            18,
            18,
            17,
            17,
            16,
            16,
            15,
            14,
            14,
            13,
            13,
            13,
            13,
            12
         ]
      }
   ],
   "title" : {
      "text" : "NeoCPAN Uploaders Monthly (Top 20)"
   }
}
