{
   "THEMA-MEDIA" : {
      "LWP-UserAgent-Caching-Simple" : {
         "5" : "open",
         "6" : "open"
      },
      "HTTP-Caching" : {
         "22" : "open",
         "16" : "merged",
         "21" : "merged",
         "20" : "merged"
      },
      "Dancer2-Plugin-HTTP-Caching" : {
         "1" : "open"
      },
      "Set-Hash-Keys" : {
         "1" : "merged"
      },
      "Dancer2-Plugin-HTTP-ContentNegotiation" : {
         "2" : "open"
      },
      "HTTP-Method" : {
         "1" : "merged"
      },
      "LWP-UserAgent-Caching" : {
         "3" : "merged",
         "1" : "merged"
      }
   },
   "plicease" : {
      "WWW-Bugzilla-BugTree" : {
         "4" : "merged"
      },
      "Dist-Zilla-Plugin-AlienBuild" : {
         "1" : "closed"
      },
      "App-cpangitify" : {
         "10" : "merged"
      },
      "Test-CChecker" : {
         "3" : "closed"
      },
      "Dist-Zilla-Plugin-CommentOut" : {
         "1" : "closed"
      },
      "Term-Clui" : {
         "5" : "merged",
         "4" : "merged"
      },
      "Alien-pkgconf" : {
         "3" : "open"
      }
   },
   "jjn1056" : {
      "DBIx-Class-ResultSet-SetControl" : {
         "1" : "open"
      },
      "Catalyst-View-Base-JSON" : {
         "1" : "open"
      },
      "Template-Lace" : {
         "2" : "open"
      },
      "Catalyst-ActionRole-Public" : {
         "1" : "open"
      },
      "Catalyst-Plugin-RedirectTo" : {
         "1" : "open"
      },
      "Catalyst-Plugin-URI" : {
         "1" : "open"
      },
      "Template-Pure" : {
         "2" : "closed",
         "11" : "open"
      },
      "Catalyst-View-MojoTemplate" : {
         "1" : "open"
      },
      "Catalyst-View-Template-Lace" : {
         "2" : "open"
      },
      "Catalyst-ControllerRole-At" : {
         "1" : "open"
      },
      "Plack-App-GraphQL" : {
         "1" : "merged"
      },
      "DBIx-Class-Migration" : {
         "117" : "merged",
         "116" : "merged"
      },
      "Catalyst-Plugin-InjectionHelpers" : {
         "3" : "open"
      },
      "WebService-Auth0" : {
         "1" : "open"
      },
      "Catalyst-Plugin-ServeFile" : {
         "1" : "open"
      },
      "MooX-TO_JSON" : {
         "1" : "open"
      },
      "Data-MuFormX-Registry" : {
         "1" : "open"
      }
   },
   "domm" : {
      "App-TimeTracker-TellRemote" : {
         "1" : "merged"
      },
      "lib-projectroot" : {
         "2" : "merged",
         "4" : "merged"
      },
      "Plack-App-ServiceStatus" : {
         "4" : "merged",
         "3" : "merged"
      },
      "Web-Request-Role-JSON" : {
         "2" : "merged"
      },
      "API-Medium" : {
         "1" : "merged",
         "2" : "open"
      },
      "DBIx-SchemaChecksum" : {
         "4" : "open"
      },
      "Catalyst-Plugin-Session-Store-Redis" : {
         "2" : "merged"
      },
      "perl-oauth2" : {
         "12" : "merged"
      },
      "Bread-Runner" : {
         "3" : "merged",
         "1" : "merged"
      },
      "Plack-Middleware-PrettyException" : {
         "1" : "merged"
      },
      "InfluxDB-LineProtocol" : {
         "13" : "merged",
         "10" : "merged"
      },
      "Web-Request-Role-Response" : {
         "1" : "merged"
      },
      "App-TimeTracker-Category" : {
         "1" : "closed"
      },
      "CtrlO-Crypt-XkcdPassword" : {
         "2" : "closed",
         "4" : "merged",
         "3" : "merged"
      },
      "App-TimeTracker" : {
         "26" : "merged",
         "18" : "merged"
      },
      "Module-ExtractUse" : {
         "21" : "merged"
      }
   },
   "LibreCat" : {
      "Plack-Middleware-Signposting" : {
         "1" : "merged"
      },
      "Catmandu-Atom" : {
         "2" : "merged"
      },
      "Catmandu-LIDO" : {
         "2" : "merged"
      },
      "Catmandu-XSD" : {
         "4" : "closed"
      },
      "Catmandu-RIS" : {
         "8" : "merged"
      },
      "Catmandu-Breaker" : {
         "5" : "merged"
      },
      "Catmandu-AlephX" : {
         "8" : "merged"
      },
      "Catmandu-Geocode" : {
         "1" : "merged"
      },
      "Catmandu-Blacklight" : {
         "1" : "merged"
      },
      "Catmandu-BagIt" : {
         "13" : "merged",
         "14" : "merged"
      },
      "Catmandu-Store-Lucy" : {
         "2" : "merged"
      },
      "Plack-App-Catmandu-Bag" : {
         "1" : "merged"
      },
      "WWW-ORCID" : {
         "3" : "merged"
      },
      "perl-oai-lib" : {
         "1" : "merged",
         "6" : "merged"
      },
      "Catmandu-SRU" : {
         "40" : "merged"
      },
      "Catmandu-FileStore" : {
         "9" : "merged",
         "10" : "merged"
      },
      "Catmandu-Identifier" : {
         "15" : "merged",
         "11" : "merged"
      },
      "Catmandu-Store-CHI" : {
         "2" : "merged",
         "1" : "merged"
      },
      "Catmandu-XLS" : {
         "17" : "merged"
      },
      "Catmandu-ArXiv" : {
         "4" : "merged"
      },
      "Catmandu-PNX" : {
         "3" : "merged"
      },
      "Catmandu-SFX" : {
         "1" : "merged"
      },
      "Catmandu-MARC" : {
         "102" : "merged",
         "103" : "merged",
         "101" : "merged"
      },
      "Catmandu-WoS" : {
         "1" : "merged"
      },
      "Catmandu" : {
         "370" : "merged",
         "371" : "merged"
      },
      "Catmandu-Zotero" : {
         "3" : "merged"
      },
      "Catmandu-LDAP" : {
         "3" : "merged"
      },
      "Catmandu-HTML" : {
         "2" : "merged"
      },
      "Catmandu-Solr" : {
         "16" : "merged"
      }
   },
   "tupinek" : {
      "Map-Tube-NizhnyNovgorod" : {
         "1" : "merged"
      },
      "Map-Tube-Kazan" : {
         "1" : "merged"
      },
      "Map-Tube-Nanjing" : {
         "1" : "merged"
      },
      "Map-Tube-Tbilisi" : {
         "1" : "open"
      },
      "Map-Tube-Moscow" : {
         "3" : "merged",
         "2" : "closed"
      },
      "Map-Tube-KualaLumpur" : {
         "1" : "merged"
      },
      "Map-Tube-Dnipropetrovsk" : {
         "1" : "merged"
      },
      "Map-Tube-Singapore" : {
         "1" : "open"
      },
      "Map-Tube-Sofia" : {
         "2" : "merged",
         "3" : "open"
      },
      "Map-Tube-Novosibirsk" : {
         "1" : "merged"
      },
      "Map-Tube-Yekaterinburg" : {
         "1" : "merged"
      },
      "Map-Tube-Minsk" : {
         "1" : "merged"
      },
      "Map-Tube-Budapest" : {
         "1" : "merged"
      },
      "Map-Tube-Kharkiv" : {
         "1" : "merged"
      },
      "Map-Tube-Prague" : {
         "1" : "merged"
      },
      "Map-Tube-SaintPetersburg" : {
         "1" : "merged"
      },
      "Map-Tube-Warsaw" : {
         "1" : "open"
      },
      "Map-Tube-Kiev" : {
         "1" : "merged"
      },
      "Map-Tube-Vienna" : {
         "1" : "open"
      },
      "Map-Tube-Malaga" : {
         "1" : "merged"
      },
      "Map-Tube-Samara" : {
         "1" : "open",
         "2" : "open"
      },
      "Map-Tube-Bucharest" : {
         "2" : "merged",
         "1" : "closed"
      }
   },
   "ziali088" : {
      "mojolicious-plugin-jsonapi" : {
         "1" : "merged",
         "2" : "merged"
      },
      "google-api-oauth-client" : {
         "3" : "merged",
         "5" : "open",
         "4" : "merged",
         "2" : "merged"
      },
      "googleapi-client" : {
         "2" : "merged"
      },
      "jsonapi-document" : {
         "3" : "merged",
         "1" : "merged"
      }
   },
   "neilb" : {
      "Proc-Pidfile" : {
         "4" : "open",
         "2" : "merged"
      },
      "Date-WeekNumber" : {
         "1" : "merged"
      },
      "Time-Duration" : {
         "1" : "open"
      },
      "again" : {
         "1" : "closed"
      },
      "constant-Atom" : {
         "1" : "open"
      },
      "Exporter-Lite" : {
         "1" : "merged"
      },
      "Lingua-EN-Numbers-Years" : {
         "1" : "merged"
      },
      "PAUSE-Packages" : {
         "7" : "merged"
      },
      "Dist-Zilla-App-Command-kwalitee" : {
         "3" : "merged"
      },
      "Const-Fast-Exporter" : {
         "2" : "open"
      },
      "Mail-SendGrid" : {
         "2" : "merged"
      },
      "CPAN-Dashboard" : {
         "2" : "merged"
      },
      "Text-Autoformat" : {
         "6" : "merged"
      },
      "Lingua-EN-Syllable" : {
         "1" : "merged"
      },
      "CPAN-ReleaseHistory" : {
         "5" : "merged"
      },
      "Net-Dict" : {
         "6" : "open"
      },
      "Class-Hook" : {
         "1" : "merged"
      },
      "PAUSE-Users" : {
         "1" : "open"
      },
      "Perl-MinimumVersion" : {
         "13" : "closed"
      },
      "DateTime-Functions" : {
         "1" : "closed"
      },
      "WebService-Speechmatics" : {
         "2" : "open"
      },
      "WebService-WordsAPI" : {
         "1" : "merged"
      },
      "Data-TreeDumper-OO" : {
         "1" : "merged"
      },
      "Text-Greeking" : {
         "1" : "closed"
      },
      "Class-Role" : {
         "1" : "open"
      },
      "Graph-ReadWrite" : {
         "2" : "merged"
      },
      "Graph" : {
         "2" : "closed"
      },
      "Text-Quote" : {
         "1" : "open"
      },
      "array-diff-perl" : {
         "1" : "merged"
      },
      "WebService-BambooHR" : {
         "1" : "merged"
      },
      "Lingua-EN-Numbers" : {
         "8" : "open"
      },
      "HTML-Summary" : {
         "2" : "closed"
      }
   },
   "bayashi" : {
      "Test-AllModules" : {
         "4" : "merged"
      },
      "Text-Chord-Piano" : {
         "2" : "merged",
         "1" : "merged"
      },
      "Plack-Middleware-EnvTracer" : {
         "2" : "merged"
      },
      "Plack-Middleware-Curlizer" : {
         "1" : "merged"
      },
      "Plack-Middleware-TimeStats" : {
         "1" : "merged",
         "2" : "merged"
      },
      "WebService-BitFlyer" : {
         "1" : "merged"
      },
      "Data-Dumper-AutoEncode" : {
         "1" : "merged"
      },
      "Sub-Data-Recursive" : {
         "1" : "merged"
      },
      "App-jl" : {
         "1" : "merged"
      },
      "Test-Arrow" : {
         "80" : "closed"
      },
      "Plack-Middleware-Debug-TraceENV" : {
         "1" : "merged"
      }
   },
   "dnmfarrell" : {
      "AWS-IP" : {
         "1" : "merged"
      },
      "XS-Tutorial" : {
         "3" : "merged"
      },
      "Encode-UTF8-Slow" : {
         "1" : "open"
      },
      "Math-HexGrid" : {
         "1" : "merged"
      },
      "IPC-Pidfile" : {
         "1" : "merged"
      },
      "App-wu" : {
         "1" : "merged"
      },
      "perldotcom" : {
         "86" : "merged",
         "98" : "merged",
         "99" : "merged",
         "97" : "merged",
         "100" : "merged",
         "104" : "merged",
         "84" : "closed",
         "102" : "merged",
         "92" : "closed",
         "73" : "merged",
         "103" : "merged",
         "105" : "merged",
         "95" : "merged",
         "101" : "merged",
         "93" : "merged"
      },
      "Test2-Tools-SkipUntil" : {
         "1" : "open"
      },
      "URI-Encode-XS" : {
         "1" : "merged"
      }
   },
   "fayland" : {
      "dist-zilla-plugin-repository" : {
         "8" : "merged",
         "9" : "merged"
      },
      "perl-Email-Sender-Transport-SMTPS" : {
         "3" : "merged"
      },
      "dist-zilla-pluginbundle-fayland" : {
         "3" : "merged",
         "2" : "merged"
      },
      "perl-WebService-AntiCaptcha" : {
         "1" : "merged"
      },
      "email-sender-transport-smtp-tls" : {
         "2" : "merged"
      },
      "perl-Business-PayPoint-MCPE" : {
         "1" : "merged"
      },
      "perl-WebService-DeathByCaptcha" : {
         "1" : "merged"
      },
      "perl-WWW-ModulrFinance" : {
         "1" : "merged"
      },
      "perl-WebService-2Captcha" : {
         "1" : "open"
      },
      "dbix-class-resultset-void" : {
         "2" : "merged",
         "1" : "merged",
         "3" : "merged"
      },
      "business-pxpay" : {
         "1" : "merged"
      },
      "perl-WWW-Yotpo" : {
         "2" : "merged"
      },
      "dist-zilla-plugin-checkchangelog" : {
         "4" : "merged"
      },
      "perl-WWW-Jirafe" : {
         "1" : "merged"
      }
   },
   "szabgab" : {
      "Syntax-Highlight-Engine-Kate" : {
         "14" : "merged"
      },
      "perlweekly" : {
         "473" : "merged",
         "516" : "merged",
         "486" : "merged",
         "395" : "merged",
         "221" : "merged",
         "273" : "merged",
         "341" : "merged",
         "303" : "merged",
         "286" : "merged",
         "244" : "merged",
         "255" : "merged",
         "496" : "merged",
         "487" : "merged",
         "517" : "merged",
         "434" : "merged",
         "214" : "merged",
         "296" : "merged",
         "287" : "merged",
         "271" : "merged",
         "507" : "merged",
         "223" : "merged",
         "301" : "merged",
         "400" : "merged",
         "266" : "merged",
         "212" : "merged",
         "432" : "merged",
         "248" : "merged",
         "249" : "merged",
         "466" : "merged",
         "370" : "merged",
         "232" : "merged",
         "410" : "merged",
         "230" : "merged",
         "449" : "merged",
         "442" : "merged",
         "378" : "merged",
         "267" : "merged",
         "419" : "merged",
         "239" : "merged",
         "440" : "merged",
         "238" : "merged",
         "418" : "merged",
         "242" : "merged",
         "365" : "merged",
         "467" : "merged",
         "240" : "merged",
         "218" : "merged",
         "493" : "merged",
         "454" : "merged",
         "235" : "merged",
         "511" : "merged",
         "254" : "merged",
         "293" : "merged",
         "277" : "merged",
         "501" : "merged",
         "307" : "merged",
         "226" : "merged",
         "281" : "merged",
         "476" : "merged",
         "513" : "merged",
         "491" : "merged",
         "245" : "merged",
         "276" : "merged",
         "524" : "merged",
         "291" : "merged",
         "227" : "merged",
         "259" : "merged",
         "258" : "merged",
         "261" : "merged",
         "458" : "merged",
         "522" : "merged",
         "528" : "merged",
         "398" : "merged",
         "263" : "merged",
         "380" : "merged",
         "250" : "merged",
         "463" : "merged",
         "252" : "merged",
         "499" : "merged",
         "280" : "merged",
         "502" : "merged",
         "498" : "merged",
         "352" : "merged",
         "282" : "merged",
         "500" : "merged",
         "363" : "merged",
         "480" : "merged",
         "510" : "merged",
         "518" : "merged",
         "488" : "merged",
         "290" : "merged",
         "489" : "merged",
         "292" : "merged",
         "288" : "merged",
         "358" : "merged",
         "490" : "merged",
         "264" : "merged",
         "289" : "merged",
         "361" : "merged",
         "492" : "merged",
         "508" : "merged",
         "383" : "merged",
         "253" : "merged",
         "376" : "merged",
         "416" : "merged",
         "462" : "merged",
         "425" : "merged",
         "236" : "merged",
         "391" : "merged",
         "247" : "merged",
         "521" : "merged",
         "494" : "merged",
         "406" : "merged",
         "260" : "merged",
         "345" : "merged",
         "216" : "merged",
         "262" : "merged",
         "436" : "merged",
         "225" : "merged",
         "447" : "merged",
         "475" : "merged",
         "268" : "merged",
         "269" : "merged",
         "523" : "merged",
         "237" : "merged",
         "251" : "merged",
         "504" : "merged",
         "246" : "merged",
         "326" : "merged",
         "315" : "merged",
         "305" : "merged",
         "275" : "merged",
         "468" : "merged",
         "484" : "merged",
         "514" : "merged",
         "217" : "merged",
         "479" : "merged",
         "265" : "merged",
         "222" : "merged",
         "220" : "merged",
         "319" : "merged",
         "279" : "merged",
         "278" : "merged",
         "465" : "merged",
         "422" : "merged",
         "420" : "merged",
         "338" : "merged",
         "300" : "merged",
         "270" : "merged",
         "428" : "merged",
         "330" : "merged",
         "272" : "merged",
         "312" : "merged",
         "229" : "merged",
         "228" : "merged",
         "472" : "merged",
         "310" : "merged",
         "231" : "merged",
         "274" : "merged",
         "257" : "merged",
         "526" : "merged",
         "485" : "merged",
         "323" : "merged",
         "243" : "merged",
         "334" : "merged",
         "211" : "merged",
         "474" : "merged",
         "505" : "merged",
         "386" : "merged",
         "256" : "merged",
         "495" : "merged",
         "527" : "merged",
         "241" : "merged",
         "413" : "merged",
         "233" : "merged",
         "224" : "merged",
         "403" : "merged",
         "213" : "merged"
      },
      "pdf-create" : {
         "4" : "merged",
         "2" : "merged",
         "1" : "merged",
         "3" : "merged",
         "5" : "merged"
      },
      "test-snapshots" : {
         "1" : "merged"
      },
      "Text-Trac" : {
         "6" : "merged"
      },
      "Web-Feed" : {
         "1" : "merged"
      },
      "whitecamel.org" : {
         "3" : "merged"
      },
      "Test-Strict" : {
         "12" : "merged",
         "13" : "merged",
         "11" : "merged",
         "14" : "merged"
      },
      "Test-CircularDependencies" : {
         "1" : "merged"
      },
      "SVG" : {
         "6" : "merged"
      }
   },
   "PerlDancer" : {
      "Dancer2-Plugin-Passphrase" : {
         "1" : "closed"
      },
      "Dancer" : {
         "1157" : "open",
         "1186" : "merged",
         "1196" : "merged"
      },
      "Dancer2-Plugin-OpenAPI" : {
         "2" : "merged"
      },
      "Dancer2-Session-Cookie" : {
         "19" : "closed"
      },
      "advent-calendar" : {
         "38" : "closed",
         "40" : "merged"
      },
      "Dancer-Session-Cookie" : {
         "8" : "closed"
      },
      "Dancer2" : {
         "1495" : "closed",
         "1114" : "merged",
         "1299" : "closed",
         "1033" : "closed",
         "1030" : "closed",
         "1364" : "merged",
         "1363" : "merged",
         "1447" : "closed",
         "1360" : "merged",
         "1505" : "closed",
         "1491" : "merged"
      },
      "Dancer2-Plugin-Auth-Extensible" : {
         "88" : "merged"
      }
   },
   "briandfoy" : {
      "file-fingerprint" : {
         "1" : "merged"
      },
      "business-isbn" : {
         "1" : "closed"
      },
      "tie-timely" : {
         "1" : "merged"
      },
      "http-size" : {
         "2" : "merged"
      },
      "mac-errors" : {
         "5" : "merged"
      },
      "business-ismn" : {
         "3" : "closed",
         "2" : "merged"
      },
      "Net-SSH-Perl-ProxiedIPC" : {
         "1" : "closed"
      },
      "string-sprintf" : {
         "1" : "merged"
      },
      "PerlPowerTools" : {
         "82" : "merged",
         "81" : "merged"
      },
      "http-cookies-mozilla" : {
         "4" : "merged"
      },
      "polyglot" : {
         "1" : "merged"
      },
      "modulino-demo" : {
         "1" : "merged"
      },
      "geo-geonames" : {
         "17" : "merged"
      },
      "module-extract-declaredversion" : {
         "2" : "closed"
      },
      "module-extract-declaredminimumperl" : {
         "1" : "merged"
      },
      "business-xisbn" : {
         "1" : "closed"
      },
      "business-isbn-data" : {
         "1" : "closed"
      },
      "cpan-packagedetails" : {
         "6" : "merged",
         "7" : "merged"
      },
      "pod-wordml" : {
         "1" : "merged"
      },
      "net-mac-vendor" : {
         "24" : "closed"
      },
      "pod-pseudopod-docbook" : {
         "3" : "closed"
      }
   },
   "sciurius" : {
      "perl-App-Packager" : {
         "1" : "merged"
      },
      "perl-File-PerlMove" : {
         "1" : "merged"
      },
      "perl-File-LoadLines" : {
         "2" : "merged",
         "3" : "merged",
         "1" : "merged"
      },
      "eps2png" : {
         "1" : "merged"
      },
      "comics" : {
         "4" : "closed",
         "7" : "open",
         "3" : "merged",
         "5" : "merged"
      },
      "perl-Data-iRealPro" : {
         "1" : "merged"
      },
      "perl-Text-Layout" : {
         "1" : "merged"
      },
      "perl-Text-Substitute" : {
         "2" : "merged"
      }
   },
   "yuki-kimoto" : {
      "Mojolicious-Plugin-SQLiteViewerLite" : {
         "2" : "open"
      },
      "Mojolicious-Plugin-DBViewer" : {
         "4" : "open"
      },
      "Rstats" : {
         "3" : "open",
         "6" : "open"
      },
      "DBIx-Custom" : {
         "11" : "merged",
         "9" : "closed"
      },
      "Mojolicious-Plugin-INIConfig" : {
         "2" : "open"
      },
      "Image-PNG-Simple" : {
         "2" : "open",
         "1" : "open"
      },
      "D" : {
         "1" : "open"
      },
      "giblog" : {
         "3" : "merged",
         "1" : "merged",
         "2" : "merged"
      },
      "Object-Simple" : {
         "9" : "open"
      },
      "Validator-Custom" : {
         "4" : "closed"
      },
      "SPVM" : {
         "51" : "merged",
         "53" : "merged",
         "18" : "merged",
         "54" : "merged",
         "13" : "merged",
         "12" : "merged",
         "14" : "merged",
         "22" : "merged"
      }
   },
   "gphat" : {
      "data-verifier" : {
         "11" : "merged",
         "12" : "merged",
         "13" : "merged",
         "15" : "merged",
         "14" : "merged",
         "10" : "merged"
      },
      "dist-zilla-pluginbundle-gphat" : {
         "1" : "open"
      },
      "chart-clicker" : {
         "50" : "merged"
      }
   },
   "srchulo" : {
      "DataTables" : {
         "17" : "merged",
         "18" : "merged"
      },
      "Catalyst--Model--Net--Stripe" : {
         "1" : "open"
      },
      "DBIx-Raw" : {
         "3" : "merged",
         "4" : "merged"
      },
      "Object-Tiny-RW-XS" : {
         "1" : "merged"
      },
      "DigitalOcean" : {
         "12" : "merged",
         "13" : "merged"
      },
      "Plack--App--HostMap" : {
         "3" : "merged"
      },
      "Short--URL" : {
         "4" : "merged",
         "3" : "merged"
      },
      "Crypt-Mode-CBC-Easy" : {
         "2" : "merged",
         "1" : "merged"
      },
      "Catalyst--Model--DBIx--Raw" : {
         "2" : "merged",
         "3" : "merged"
      },
      "Image--Imlib2--Thumbnail--Scaled" : {
         "2" : "merged",
         "1" : "merged"
      },
      "Short-URL" : {
         "6" : "merged"
      },
      "jQuery-File-Upload" : {
         "2" : "merged",
         "1" : "merged"
      },
      "Mojolicious-Static-Role-Compressed" : {
         "2" : "merged"
      },
      "Web-Authenticate" : {
         "4" : "merged",
         "3" : "merged"
      },
      "Mojolicious-Command-bcrypt" : {
         "1" : "merged"
      }
   },
   "mohawk2" : {
      "xml-saxon-xslt3" : {
         "1" : "merged"
      },
      "Alien-Gimp" : {
         "1" : "merged"
      },
      "Event-Stats" : {
         "1" : "merged"
      },
      "moox-stricthas" : {
         "1" : "closed",
         "2" : "merged"
      },
      "moox-thunking" : {
         "4" : "merged"
      },
      "Mail-POP3" : {
         "1" : "merged"
      },
      "cpan-Event" : {
         "4" : "merged"
      },
      "SQL-Translator-Parser-OpenAPI" : {
         "1" : "merged"
      },
      "Inline-Struct" : {
         "5" : "merged"
      }
   },
   "benkasminbullock" : {
      "Directory-Diff" : {
         "2" : "merged",
         "4" : "closed",
         "3" : "closed"
      },
      "JSON-Parse" : {
         "39" : "merged"
      },
      "Text-Fuzzy" : {
         "15" : "closed"
      },
      "Geo-GNS" : {
         "1" : "merged"
      },
      "Lingua-JA-Moji" : {
         "22" : "merged"
      },
      "net-ipv6addr" : {
         "2" : "closed"
      },
      "Lingua-EN-PluralToSingular" : {
         "20" : "open"
      },
      "gzip-faster" : {
         "4" : "merged"
      },
      "html-make" : {
         "5" : "merged"
      },
      "image-png-qrcode" : {
         "2" : "merged"
      }
   },
   "bluefeet" : {
      "GitLab-API-v4" : {
         "2" : "closed"
      },
      "Games-EveOnline-API" : {
         "9" : "merged"
      },
      "Curio-Role-DBIx-Connector" : {
         "1" : "open"
      },
      "Catalyst-Model-Curio" : {
         "2" : "merged"
      },
      "Curio" : {
         "1" : "merged"
      },
      "MooX-BuildArgs" : {
         "8" : "merged",
         "1" : "closed"
      },
      "Data-Xslate" : {
         "3" : "merged"
      },
      "GIS-Distance" : {
         "7" : "merged"
      },
      "Net-Gitlab" : {
         "1" : "merged"
      },
      "MooseX-SingleArg" : {
         "6" : "merged"
      },
      "MooX-PluginKit" : {
         "1" : "open"
      },
      "MooX-Emulate-Class-Accessor-Fast" : {
         "2" : "merged"
      }
   },
   "noxxi" : {
      "p5-mail-dmarc-iterator" : {
         "1" : "merged"
      },
      "p5-net-inspect" : {
         "1" : "merged"
      },
      "p5-io-socket-ssl" : {
         "79" : "merged"
      },
      "p5-net-imp" : {
         "2" : "merged"
      },
      "p5-mail-dkim-iterator" : {
         "1" : "merged"
      },
      "p5-net-sslglue" : {
         "5" : "merged"
      },
      "p5-net-sip" : {
         "11" : "merged"
      },
      "p5-mail-spf-iterator" : {
         "2" : "closed",
         "3" : "merged"
      },
      "p5-app-dubioushttp" : {
         "5" : "merged"
      }
   },
   "Corion" : {
      "Spreadsheet-ReadSXC" : {
         "4" : "merged"
      },
      "HTTP-Request-FromCurl" : {
         "1" : "closed"
      },
      "filter-signatures" : {
         "3" : "merged"
      },
      "html-rebase" : {
         "1" : "closed"
      },
      "HTTP-Request-Generator" : {
         "2" : "closed"
      },
      "Meetup-API" : {
         "1" : "merged"
      },
      "WWW-Mechanize-Shell" : {
         "4" : "merged"
      },
      "Mail-URLFor" : {
         "1" : "merged"
      },
      "Finance-Bank-Postbank_de" : {
         "3" : "merged"
      },
      "Test-HTTP-LocalServer" : {
         "5" : "merged"
      },
      "WWW-Mechanize-Chrome" : {
         "5" : "closed"
      },
      "dbd-wmi" : {
         "2" : "merged"
      },
      "WWW-Google-Login" : {
         "1" : "merged"
      }
   },
   "stevan" : {
      "p5-Moxie" : {
         "5" : "merged"
      },
      "p5-Method-Traits" : {
         "1" : "merged",
         "2" : "merged"
      },
      "BreadBoard" : {
         "63" : "merged",
         "67" : "merged"
      },
      "p5-Directory-Scanner" : {
         "1" : "merged"
      },
      "p5-UNIVERSAL-Object" : {
         "2" : "closed",
         "13" : "merged"
      },
      "p5-decorators" : {
         "6" : "merged"
      },
      "tree-simple" : {
         "9" : "merged",
         "10" : "merged"
      },
      "tree-simple-sax" : {
         "1" : "merged"
      },
      "promises-perl" : {
         "79" : "merged",
         "84" : "merged"
      },
      "p5-MOP" : {
         "15" : "merged"
      },
      "Path-Router" : {
         "10" : "merged"
      },
      "p5-plack-debugger" : {
         "14" : "merged"
      }
   },
   "davorg" : {
      "net-songkick" : {
         "6" : "merged",
         "4" : "merged"
      },
      "xml-feed" : {
         "52" : "merged",
         "49" : "merged",
         "54" : "merged"
      },
      "tie-hash-cannabinol" : {
         "3" : "merged"
      },
      "symbol-approx-sub" : {
         "30" : "merged",
         "29" : "merged"
      },
      "svg-trafficlight" : {
         "1" : "merged",
         "3" : "merged",
         "2" : "merged"
      },
      "array-compare" : {
         "6" : "merged",
         "2" : "merged",
         "7" : "merged",
         "5" : "merged",
         "9" : "merged",
         "10" : "merged"
      },
      "audiofile-info-mp3-id3lib" : {
         "1" : "merged"
      },
      "perlanet" : {
         "6" : "merged"
      },
      "Ogg-Vorbis-Header" : {
         "1" : "merged"
      },
      "parse-rpm-spec" : {
         "2" : "merged"
      },
      "qmail-queuehandler" : {
         "4" : "merged"
      },
      "calendar-simple" : {
         "1" : "merged",
         "2" : "merged"
      },
      "dashboard" : {
         "37" : "merged"
      },
      "genealogy-ahnentafel" : {
         "2" : "merged"
      },
      "tie-hash-regex" : {
         "2" : "merged"
      },
      "moox-role-json_ld" : {
         "24" : "merged",
         "3" : "merged",
         "12" : "merged"
      },
      "template-plugin-audiofile-info" : {
         "1" : "merged"
      },
      "svg-christmastree" : {
         "8" : "merged",
         "9" : "merged",
         "3" : "merged"
      }
   },
   "rjbs" : {
      "Module-Faker" : {
         "12" : "merged"
      },
      "Email-Stuffer" : {
         "49" : "closed"
      },
      "JSON-Typist" : {
         "3" : "closed"
      },
      "MooseX-ClassCompositor" : {
         "3" : "merged"
      },
      "Time-Piece" : {
         "29" : "open"
      },
      "Email-Valid" : {
         "21" : "closed"
      },
      "Getopt-Long-Descriptive" : {
         "22" : "closed"
      },
      "Dist-Zilla" : {
         "488" : "closed",
         "498" : "closed"
      },
      "Test-Deep" : {
         "74" : "closed"
      },
      "Dist-Zilla-PluginBundle-RJBS" : {
         "7" : "closed"
      },
      "Test-Abortable" : {
         "1" : "closed"
      },
      "Test-Routine" : {
         "12" : "closed"
      }
   },
   "pplu" : {
      "moosex-datamodel" : {
         "10" : "open"
      },
      "paws-net-multiplexcaller" : {
         "1" : "merged"
      },
      "kubernetes-builder" : {
         "1" : "open"
      },
      "aws-sdk-perl" : {
         "137" : "merged"
      },
      "AWSv4Signer" : {
         "1" : "merged"
      },
      "cfn-perl" : {
         "7" : "merged"
      },
      "datastruct-flat" : {
         "1" : "merged"
      },
      "io-k8s-p5" : {
         "1" : "merged"
      },
      "kubectl-cliwrapper" : {
         "2" : "merged",
         "1" : "merged"
      },
      "kubernetes-rest" : {
         "1" : "open"
      },
      "docker-registry" : {
         "2" : "merged",
         "16" : "merged"
      },
      "swagger-schema-kubernetes" : {
         "1" : "open"
      },
      "cloudhealth-api-perl" : {
         "1" : "merged"
      },
      "azure-ad-auth" : {
         "3" : "merged",
         "2" : "merged"
      },
      "aws-networks" : {
         "1" : "merged"
      }
   },
   "salva" : {
      "p5-Pg-PQ" : {
         "3" : "open"
      },
      "p5-Net-OpenSSH" : {
         "13" : "closed",
         "15" : "closed"
      },
      "p5-AnyEvent-FileLock" : {
         "3" : "open"
      },
      "p5-Math-Vector-Real-Polyline" : {
         "1" : "open"
      },
      "p5-Hash-Spy" : {
         "1" : "merged",
         "2" : "open"
      },
      "p5-Win32-EnumPrinters" : {
         "1" : "open"
      },
      "p5-Sort-Packed" : {
         "1" : "open"
      },
      "p5-Win32-Ldd" : {
         "2" : "open",
         "1" : "merged"
      },
      "p5-Net-OpenSSH-Parallel" : {
         "4" : "merged"
      },
      "p5-Config-Find" : {
         "4" : "open"
      },
      "p5-Math-Geometry-IntersectionArea" : {
         "2" : "open",
         "1" : "merged"
      },
      "p5-Sort-Key-Domain" : {
         "2" : "open",
         "1" : "merged"
      },
      "p5-Math-Vector-Real-XS" : {
         "1" : "open"
      },
      "p5-Net-SFTP-Foreign" : {
         "11" : "merged"
      },
      "p5-Math-Vector-Real" : {
         "1" : "open"
      }
   },
   "oalders" : {
      "http-cookiemonster" : {
         "2" : "merged",
         "3" : "merged"
      },
      "lwp-consolelogger" : {
         "10" : "merged",
         "11" : "merged"
      },
      "archive-any" : {
         "8" : "merged",
         "6" : "merged"
      },
      "webservice-sqlformat" : {
         "5" : "merged",
         "6" : "merged"
      },
      "module-version-loaded" : {
         "1" : "merged"
      },
      "uri-parsesearchstring-more" : {
         "3" : "merged"
      },
      "datetime-format-paypal-ipn" : {
         "2" : "merged",
         "1" : "merged"
      },
      "open-this" : {
         "4" : "merged"
      },
      "dbix-mysql-replication-slave" : {
         "1" : "merged"
      },
      "business-paypal-api" : {
         "14" : "merged",
         "8" : "merged",
         "15" : "merged"
      },
      "plack-middleware-nodeflate" : {
         "1" : "merged"
      },
      "http-browserdetect" : {
         "166" : "merged",
         "144" : "merged",
         "145" : "merged"
      }
   },
   "team-at-cpan" : {
      "Net-Async-Pusher" : {
         "1" : "merged"
      },
      "Database-Async" : {
         "1" : "open"
      },
      "WebService-Amazon-DynamoDB" : {
         "1" : "merged"
      },
      "WebService-Async-UserAgent" : {
         "1" : "merged"
      },
      "Ryu" : {
         "1" : "open",
         "5" : "merged"
      },
      "Tickit-Widget-Term" : {
         "1" : "merged"
      },
      "Tickit-Widget-LogAny" : {
         "1" : "merged"
      },
      "Tickit-Widget-Figlet" : {
         "1" : "merged"
      },
      "Net-Async-Redis" : {
         "11" : "merged",
         "6" : "merged"
      },
      "Ryu-Async" : {
         "1" : "open"
      },
      "Net-Async-Trello" : {
         "5" : "merged"
      }
   },
   "eserte" : {
      "p5-Kwalify" : {
         "5" : "open",
         "4" : "merged"
      },
      "tk-pathentry" : {
         "1" : "merged",
         "2" : "open"
      },
      "cpan-test-dummy-perl5-buildrequires" : {
         "1" : "merged"
      },
      "tk-dateentry" : {
         "2" : "merged"
      },
      "xterm-conf" : {
         "1" : "merged"
      },
      "image-info" : {
         "9" : "merged"
      },
      "imager-image-base" : {
         "1" : "merged"
      },
      "tk-tiff" : {
         "1" : "merged"
      },
      "cpan-test-dummy-perl5-requires" : {
         "1" : "merged"
      },
      "Map-Tube-Berlin" : {
         "1" : "merged",
         "3" : "merged",
         "6" : "merged",
         "4" : "merged",
         "2" : "merged",
         "5" : "merged"
      },
      "tk-histentry" : {
         "2" : "open",
         "1" : "merged"
      },
      "Slay-Makefile" : {
         "4" : "merged"
      },
      "tk-jpeg-lite" : {
         "1" : "merged"
      },
      "tk-flatcheckbox" : {
         "1" : "merged"
      },
      "tk-fontdialog" : {
         "5" : "merged",
         "2" : "merged"
      },
      "cpan-plugin-sysdeps" : {
         "3" : "merged",
         "4" : "merged"
      }
   },
   "jhthorsen" : {
      "w3c-validator-server" : {
         "2" : "merged"
      },
      "app-git-ship" : {
         "23" : "merged"
      },
      "mojo-mysql" : {
         "62" : "merged"
      },
      "mandel" : {
         "32" : "open"
      },
      "mojo-redis" : {
         "44" : "merged"
      },
      "openapi-client" : {
         "11" : "merged"
      },
      "mojolicious-plugin-openapi" : {
         "98" : "merged"
      },
      "app-tt" : {
         "2" : "merged"
      },
      "toadfarm" : {
         "26" : "merged"
      },
      "json-validator" : {
         "88" : "closed",
         "11" : "merged"
      }
   },
   "binary-com" : {
      "perl-feed-phasecheck" : {
         "1" : "open"
      },
      "perl-Format-Util" : {
         "3" : "open"
      },
      "perl-Test-NoLeaks" : {
         "5" : "merged"
      },
      "perl-Email-Stuffer-TestLinks" : {
         "3" : "open"
      },
      "perl-Date-Utility" : {
         "6" : "closed",
         "9" : "merged"
      },
      "perl-Data-Validate-Sanctions" : {
         "8" : "open"
      },
      "perl-Email-Folder-Search" : {
         "2" : "merged"
      },
      "perl-Math-Random-Normal-Leva" : {
         "6" : "merged"
      },
      "dogstatsd-perl" : {
         "10" : "open"
      },
      "perl-Finance-Contract" : {
         "31" : "open"
      },
      "perl-Mojo-WebSocketProxy" : {
         "41" : "open"
      },
      "perl-Crypt-NamedKeys" : {
         "6" : "open"
      },
      "perl-Maths-Gauss-XS" : {
         "1" : "merged"
      },
      "perl-CSV-HistoryPlayer" : {
         "10" : "open"
      },
      "perl-Data-Chronicle" : {
         "35" : "open"
      },
      "perl-Ethereum-RPC-Client" : {
         "10" : "closed"
      },
      "perl-Math-Business-BlackScholesMerton" : {
         "22" : "open"
      },
      "perl-Locale-Country-Extra" : {
         "15" : "open"
      },
      "perl-Time-Duration-Concise-Localize" : {
         "14" : "open"
      }
   },
   "barbie" : {
      "cpan-testers-www-wiki" : {
         "1" : "merged"
      },
      "cpan-testers-www-preferences" : {
         "1" : "merged"
      },
      "www-scraper-isbn-wheelers_driver" : {
         "1" : "merged"
      },
      "lingua-en-namecase" : {
         "1" : "open"
      },
      "calendar-list" : {
         "2" : "merged",
         "1" : "merged",
         "3" : "merged"
      },
      "cpan-testers-www-statistics" : {
         "7" : "merged"
      },
      "devel-platform-info" : {
         "4" : "merged",
         "5" : "merged"
      },
      "cpan-testers-www-reports" : {
         "7" : "open"
      },
      "acme-cpanauthors-british" : {
         "4" : "merged",
         "3" : "merged"
      }
   },
   "jkeenan" : {
      "perl5-build-warnings" : {
         "1" : "open"
      },
      "File-Path" : {
         "6" : "open"
      },
      "cpan-mini-visit-simple" : {
         "1" : "merged"
      },
      "CPAN-Cpanorg-Auxiliary" : {
         "1" : "closed",
         "2" : "open"
      },
      "test-against-dev" : {
         "1" : "closed",
         "3" : "closed"
      },
      "CPAN-cpanminus-reporter-RetainReports" : {
         "1" : "merged"
      },
      "regexp-functions" : {
         "1" : "open"
      },
      "rt2github" : {
         "1" : "closed"
      },
      "parse-taxonomy" : {
         "1" : "open"
      },
      "pod-multi" : {
         "1" : "open"
      },
      "parse-file-metadata" : {
         "1" : "open"
      },
      "devel-git-multibisect" : {
         "2" : "closed",
         "1" : "closed",
         "3" : "closed"
      },
      "string-perlidentifier" : {
         "1" : "open"
      },
      "text-csv-hashify" : {
         "3" : "open"
      }
   },
   "nigelhorne" : {
      "DateTime-Format-Genealogy" : {
         "2" : "merged",
         "3" : "open",
         "1" : "merged"
      },
      "Geo-Coder-List" : {
         "1" : "merged"
      },
      "CGI-Info" : {
         "2" : "merged"
      },
      "Geo-Coder-US-Census" : {
         "33" : "closed"
      },
      "Geo-Coder-Postcodes" : {
         "1" : "merged"
      },
      "CGI-Lingua" : {
         "21" : "merged"
      }
   },
   "houseabsolute" : {
      "DateTime-TimeZone" : {
         "32" : "closed"
      },
      "perl-code-tidyall" : {
         "52" : "closed"
      },
      "DateTime-Format-Strptime" : {
         "17" : "closed"
      },
      "DateTime-Locale" : {
         "6" : "merged",
         "7" : "closed",
         "9" : "merged",
         "8" : "merged"
      },
      "DateTime.pm" : {
         "84" : "closed"
      }
   },
   "jgamble" : {
      "Math-Fortran" : {
         "1" : "merged"
      },
      "Convert-Base81" : {
         "1" : "merged"
      },
      "Logic-TruthTable" : {
         "2" : "merged",
         "1" : "closed"
      },
      "Math-Polynomial-Solve" : {
         "1" : "merged"
      },
      "Math-Utils" : {
         "6" : "open"
      },
      "Convert-Base85" : {
         "3" : "merged",
         "2" : "closed"
      },
      "Math-Derivative" : {
         "1" : "merged"
      },
      "Algorithm-QuineMcCluskey" : {
         "2" : "merged",
         "1" : "closed"
      }
   },
   "mschout" : {
      "perl-number-phone-formatter-epp" : {
         "2" : "merged"
      },
      "perl-math-currency" : {
         "2" : "merged"
      },
      "number-phone-countrycode" : {
         "1" : "closed"
      },
      "perl-text-template" : {
         "1" : "merged"
      },
      "template-plugin-map" : {
         "1" : "closed"
      },
      "apache-authcookie" : {
         "8" : "merged"
      },
      "apache-authticket" : {
         "1" : "open"
      },
      "perl-log-dispatch-filerotate" : {
         "22" : "merged"
      }
   },
   "yanick" : {
      "MsgPack-RPC" : {
         "12" : "closed"
      },
      "Dist-Zilla-Stash-Contributors" : {
         "1" : "merged"
      },
      "MoobX" : {
         "9" : "merged"
      },
      "Dancer2-Plugin-FontSubset" : {
         "1" : "merged"
      },
      "Taskwarrior-Kusarigama" : {
         "29" : "closed"
      },
      "Template-Caribou" : {
         "3" : "closed"
      },
      "Dancer2-Plugin-Showterm" : {
         "3" : "merged",
         "1" : "merged"
      },
      "Term-Caca" : {
         "10" : "open"
      },
      "Template-Mustache" : {
         "53" : "closed"
      },
      "moosex-blessed-reconstruct" : {
         "6" : "open"
      },
      "perl-json-schema-shorthand" : {
         "2" : "open"
      },
      "pollux" : {
         "5" : "merged"
      },
      "Dist-Zilla-Plugin-SchwartzRatio" : {
         "5" : "open"
      },
      "List-Lazy" : {
         "5" : "open"
      },
      "Dancer2-Plugin-WebSocket" : {
         "7" : "closed",
         "4" : "merged"
      },
      "xml-xpathscript" : {
         "2" : "open",
         "1" : "merged"
      },
      "Escape-Houdini" : {
         "5" : "closed"
      },
      "Dancer-Template-Handlebars" : {
         "3" : "merged"
      }
   },
   "derf" : {
      "App-Raps2" : {
         "2" : "merged"
      },
      "Travel-Status-DE-VRR" : {
         "2" : "merged"
      },
      "dthumb" : {
         "3" : "merged"
      },
      "Travel-Status-DE-DeutscheBahn" : {
         "2" : "merged",
         "3" : "merged"
      },
      "App-Hashl" : {
         "2" : "merged"
      },
      "icli" : {
         "20" : "merged"
      },
      "Travel-Status-DE-IRIS" : {
         "8" : "open"
      },
      "Travel-Routing-DE-VRR" : {
         "10" : "open"
      },
      "Travel-Status-DE-URA" : {
         "8" : "merged"
      }
   },
   "FGasper" : {
      "p5-Net-ACME" : {
         "2" : "merged"
      },
      "p5-Text-Control" : {
         "1" : "merged"
      },
      "p5-Math-ProvablePrime" : {
         "1" : "merged"
      },
      "p5-Crypt-Perl" : {
         "10" : "merged",
         "9" : "closed",
         "11" : "merged",
         "1" : "merged"
      },
      "p5-Socket-MsgHdr" : {
         "1" : "open"
      },
      "p5-Call-Context" : {
         "1" : "merged"
      },
      "p5-IO-Framed" : {
         "2" : "merged"
      },
      "p5-Crypt-Format" : {
         "1" : "merged"
      },
      "p5-Net-WebSocket" : {
         "6" : "merged",
         "2" : "merged"
      },
      "p5-Net-ACME2" : {
         "1" : "merged"
      },
      "p5-Net-Curl-Promiser" : {
         "1" : "merged"
      },
      "p5-Linux-Perl" : {
         "3" : "merged",
         "2" : "closed"
      },
      "p5-X-Tiny" : {
         "1" : "closed"
      },
      "p5-CBOR-Free" : {
         "2" : "merged"
      },
      "p5-Protocol-DBus" : {
         "1" : "merged"
      },
      "p5-Symbol-Get" : {
         "1" : "merged"
      },
      "p5-DNS-Unbound" : {
         "1" : "merged"
      },
      "p5-Crypt-RSA-Parse" : {
         "3" : "merged"
      }
   },
   "robrwo" : {
      "Template-Plugin-Path-Tiny" : {
         "1" : "open"
      },
      "Hash-Util-Merge" : {
         "2" : "closed"
      },
      "Imager-Bing-MapLayer" : {
         "15" : "merged"
      },
      "Linux-Statm-Tiny" : {
         "11" : "merged"
      },
      "Struct-Flatten-Template" : {
         "2" : "open"
      },
      "Types-Const" : {
         "5" : "merged"
      },
      "Test-Roo-DataDriven" : {
         "5" : "merged"
      },
      "File-Temp-Trace" : {
         "1" : "merged"
      },
      "MooX-NonOO" : {
         "4" : "merged"
      },
      "File-Rotate-Simple" : {
         "9" : "merged",
         "1" : "merged",
         "5" : "closed"
      },
      "MooX-Should" : {
         "1" : "merged",
         "2" : "merged"
      },
      "Lingua-Conjunction" : {
         "1" : "merged"
      },
      "HTML-FormHandlerX-Widget-Field-Template" : {
         "1" : "merged"
      },
      "SemanticWeb-Schema" : {
         "1" : "merged"
      },
      "MooX-Failover" : {
         "4" : "closed"
      },
      "Hash-Match" : {
         "6" : "merged"
      },
      "Tree-Node" : {
         "2" : "open"
      }
   },
   "preaction" : {
      "Mercury" : {
         "31" : "merged",
         "42" : "merged"
      },
      "Mojolicious-Plugin-Moai" : {
         "1" : "merged"
      },
      "Yancy" : {
         "5" : "merged",
         "28" : "merged",
         "19" : "merged",
         "65" : "closed",
         "66" : "merged",
         "16" : "merged",
         "68" : "merged",
         "63" : "merged",
         "1" : "merged",
         "7" : "closed"
      },
      "Pod-Usage-Return" : {
         "4" : "merged"
      },
      "Term-FormatColumns" : {
         "4" : "merged"
      },
      "Mojolicious-Plugin-DBIC" : {
         "2" : "closed"
      },
      "Test-Import" : {
         "4" : "merged"
      },
      "List-Slice" : {
         "2" : "merged"
      },
      "Alien-SwaggerUI" : {
         "1" : "merged"
      },
      "Beam-Wire" : {
         "67" : "merged"
      },
      "Beam-Minion" : {
         "2" : "merged"
      },
      "Git-ReleaseRepo" : {
         "25" : "merged"
      },
      "Statocles" : {
         "546" : "merged"
      },
      "Yancy-Backend-Static" : {
         "9" : "merged",
         "1" : "merged"
      }
   },
   "ingydotnet" : {
      "inline-pm" : {
         "74" : "open"
      },
      "Inline-Java" : {
         "6" : "merged"
      },
      "swim-pm" : {
         "36" : "open"
      },
      "yaml-libyaml-pm" : {
         "83" : "closed"
      },
      "inline-c-pm" : {
         "68" : "merged",
         "90" : "merged"
      },
      "pegex-pm" : {
         "70" : "merged"
      },
      "module-package-ingy-pm" : {
         "2" : "open"
      },
      "module-package-pm" : {
         "2" : "open"
      },
      "test-base-pm" : {
         "20" : "open"
      }
   },
   "reneeb" : {
      "EPublisher-Source-Plugin-MetaCPAN" : {
         "4" : "merged",
         "1" : "merged"
      },
      "Data-Validate-WithYAML-Plugin-Phone" : {
         "3" : "merged",
         "1" : "merged",
         "4" : "open",
         "2" : "merged"
      },
      "Text-Find-Scalar" : {
         "1" : "merged"
      },
      "perl-Tropo" : {
         "1" : "merged"
      },
      "Data-Validate-WithYAML-Plugin-NoSpam" : {
         "2" : "merged",
         "3" : "merged",
         "1" : "merged"
      },
      "OTRS-OPM-Analyzer" : {
         "2" : "merged",
         "3" : "merged"
      },
      "Mojolicious-Plugin-SecurityHeader" : {
         "1" : "merged",
         "2" : "merged"
      },
      "Test-CheckManifest" : {
         "8" : "merged",
         "18" : "merged",
         "17" : "merged",
         "5" : "merged"
      },
      "App-CPANCoverBadge" : {
         "1" : "merged"
      },
      "perl-Nexmo-SMS" : {
         "5" : "merged"
      },
      "HTTP-Tiny-Multipart" : {
         "7" : "open",
         "5" : "merged"
      },
      "Mojolicious-Plugin-AdditionalValidationChecks" : {
         "4" : "merged",
         "3" : "merged"
      },
      "Data-Validate-WithYAML" : {
         "1" : "merged",
         "2" : "open"
      },
      "Parse-WWWAuthenticate" : {
         "2" : "merged",
         "1" : "merged"
      },
      "OTRS-OPM-Parser" : {
         "1" : "merged",
         "2" : "merged"
      },
      "Mojolicious-Command-generate-localplugin" : {
         "2" : "merged"
      },
      "MySQL-Workbench-Parser" : {
         "3" : "merged"
      },
      "HTTP-Tiny-FromHTTPRequest" : {
         "1" : "merged"
      },
      "Mojolicious-Plugin-WebAPI" : {
         "2" : "merged"
      },
      "Wx-Perl-DirTree" : {
         "1" : "merged"
      },
      "Mojolicious-Plugin-BootstrapAlerts" : {
         "2" : "merged"
      },
      "Mojolicious-Plugin-TagHelpersI18N" : {
         "2" : "merged",
         "1" : "merged"
      },
      "MySQL-Workbench-SQLiteSimple" : {
         "1" : "merged"
      },
      "MySQL-Workbench-DBIC" : {
         "4" : "merged",
         "12" : "merged",
         "17" : "merged"
      },
      "Mojolicious-Plugin-Data-Validate-WithYAML" : {
         "1" : "merged"
      },
      "Data-Tabulate" : {
         "1" : "merged",
         "2" : "merged"
      },
      "EPublisher-Source-Plugin-PerltutsCom" : {
         "3" : "merged",
         "5" : "closed",
         "2" : "merged"
      },
      "Mojolicious-Plugin-JSLoader" : {
         "2" : "merged"
      },
      "Data-Validate-WithYAML-Plugin-EMail" : {
         "1" : "merged",
         "3" : "merged",
         "2" : "merged"
      },
      "Data-Validate-WithYAML-Plugin-IBAN" : {
         "2" : "merged",
         "1" : "merged"
      },
      "Data-Validate-WithYAML-Plugin-PasswordPolicy" : {
         "2" : "merged",
         "3" : "merged",
         "1" : "merged"
      },
      "Data-Tabulate-Plugin-ASCIITable" : {
         "2" : "merged",
         "1" : "merged"
      },
      "Mojolicious-Plugin-JavaScript-Console" : {
         "1" : "merged"
      },
      "EPublisher" : {
         "1" : "merged",
         "3" : "merged",
         "2" : "merged"
      },
      "Tie-CheckVariables" : {
         "5" : "merged",
         "2" : "closed"
      },
      "Perl-Critic-RENEEB" : {
         "2" : "open",
         "1" : "merged"
      },
      "MojoX-Encode-Gzip" : {
         "2" : "merged"
      },
      "Mojolicious-Plugin-CSSLoader" : {
         "1" : "merged"
      },
      "Mojolicious-Plugin-NoReferrer" : {
         "1" : "merged"
      },
      "Mojolicious-Plugin-FormFieldsFromJSON" : {
         "7" : "merged"
      },
      "Data-Validate-WithYAML-Plugin-Country" : {
         "2" : "merged",
         "1" : "merged"
      },
      "Mojolicious-Plugin-Prove" : {
         "2" : "merged"
      },
      "Data-Validate-WithYAML-Plugin-URL" : {
         "1" : "merged",
         "3" : "merged",
         "2" : "merged"
      },
      "OData-QueryParams-DBIC" : {
         "3" : "merged",
         "1" : "merged"
      },
      "HTTP-Tiny-FileProtocol" : {
         "1" : "merged"
      },
      "Padre-Plugin-RegexExplain" : {
         "1" : "merged",
         "2" : "merged"
      },
      "EPublisher-Target-Plugin-EPub" : {
         "1" : "merged",
         "2" : "merged"
      },
      "Test-TestCoverage" : {
         "1" : "merged"
      },
      "Class-Superclasses" : {
         "1" : "merged",
         "3" : "merged"
      },
      "Map-Tube-Frankfurt" : {
         "5" : "merged",
         "1" : "merged",
         "3" : "merged",
         "7" : "merged"
      },
      "MojoX-GlobalEvents" : {
         "2" : "open",
         "1" : "merged"
      },
      "OPAR" : {
         "69" : "merged",
         "70" : "merged"
      },
      "EPublisher-Target-Plugin-OTRSDoc" : {
         "2" : "merged",
         "1" : "merged",
         "3" : "merged"
      },
      "OTRS-OPM-Maker" : {
         "4" : "merged",
         "3" : "merged"
      },
      "Data-Tabulate-Plugin-HTMLTable" : {
         "1" : "merged",
         "2" : "merged"
      },
      "HTML-Template-Compiled-Plugins-RENEEB" : {
         "2" : "merged",
         "1" : "merged"
      },
      "Padre-Plugin-DistZilla" : {
         "1" : "merged",
         "2" : "open"
      }
   },
   "markov2" : {
      "perl5-Object-Realize-Later" : {
         "1" : "closed"
      },
      "perl5-Mail-Message" : {
         "1" : "closed"
      },
      "perl5-User-Identity" : {
         "1" : "closed"
      },
      "perl5-Any-Daemon-HTTP" : {
         "1" : "merged"
      },
      "perl5-Any-Daemon" : {
         "1" : "merged"
      },
      "perl5-Log-Report-Optional" : {
         "1" : "closed"
      },
      "perl5-Log-Report-Template" : {
         "1" : "closed"
      },
      "perl5-String-Print" : {
         "1" : "closed"
      },
      "perl5-Log-Report-Lexicon" : {
         "1" : "closed"
      },
      "perl5-Log-Report" : {
         "1" : "closed"
      },
      "perl5-Mail-Box" : {
         "1" : "merged"
      }
   },
   "ivanwills" : {
      "App-Git-Workflow-Command-Take" : {
         "1" : "open"
      },
      "GetOpt-Alt" : {
         "1" : "merged",
         "3" : "open"
      },
      "SVG-Calendar" : {
         "1" : "merged"
      },
      "App-used" : {
         "1" : "open"
      },
      "App-bitbucket-cli" : {
         "1" : "open"
      },
      "App-diffdir" : {
         "2" : "open"
      },
      "Group-Git-Cmd-SinceRelease" : {
         "1" : "open"
      },
      "Group-Git-Taggers-Perl" : {
         "1" : "merged"
      },
      "VCS-Which" : {
         "1" : "merged"
      },
      "Data-Context" : {
         "1" : "open"
      }
   },
   "naturalist" : {
      "Mojolicious--Plugin--Bcrypt" : {
         "5" : "merged"
      },
      "kelp-module-bcrypt" : {
         "1" : "merged"
      },
      "pod-markdown-github" : {
         "10" : "merged",
         "4" : "merged"
      },
      "kelp-module-config-yaml" : {
         "1" : "merged"
      },
      "Validate--Tiny" : {
         "9" : "merged"
      },
      "kelp-module-template-xslate" : {
         "1" : "merged"
      },
      "kelp-module-rdbo" : {
         "3" : "merged"
      },
      "kelp-module-template-toolkit" : {
         "2" : "merged"
      },
      "kelp-module-json-xs" : {
         "1" : "merged"
      },
      "perl-html-formatnroff" : {
         "2" : "merged"
      }
   }
}
