{
   "series" : [
      {
         "data" : [
            -318,
            -189,
            -187,
            -115,
            -35,
            -27,
            -13,
            -12,
            -11,
            -10
         ],
         "name" : "Current Chain",
         "meta" : [
            "ETHER",
            "PERLANCAR",
            "MANWAR",
            "IVANWILLS",
            "MGV",
            "Perl6",
            "OLIVER",
            "KIMOTO",
            "EXODIST",
            "IVANYCH"
         ]
      },
      {
         "meta" : [
            "ETHER",
            "FREW",
            "PERLANCAR",
            "MANWAR",
            "BARBIE",
            "TOBYINK",
            "CJM",
            "MGV",
            "BOOK",
            "BINGOS"
         ],
         "name" : "Longest Chain",
         "data" : [
            318,
            200,
            189,
            187,
            165,
            133,
            132,
            130,
            129,
            125
         ]
      }
   ],
   "title" : {
      "text" : "CPAN Regulars Weekly (Top 10)"
   },
   "subtitle" : {
      "text" : "Last updated at 2018-04-03 12:00:02 GMT"
   }
}
