{
   "subtitle" : {
      "text" : "Last updated at 2020-02-02 00:00:02 GMT"
   },
   "title" : {
      "text" : "CPAN Regulars Weekly (Top 10)"
   },
   "series" : [
      {
         "name" : "Current Chain",
         "data" : [
            -413,
            -284,
            -122,
            -16,
            -14,
            -10,
            -9,
            -8,
            -5,
            -5
         ],
         "meta" : [
            "ETHER",
            "PERLANCAR",
            "Perl6",
            "TOBYINK",
            "FELIPE",
            "SHLOMIF",
            "WYANT",
            "REEDFISH",
            "DAGOLDEN",
            "PABLROD"
         ]
      },
      {
         "name" : "Longest Chain",
         "data" : [
            413,
            284,
            270,
            200,
            177,
            165,
            133,
            132,
            130,
            129
         ],
         "meta" : [
            "ETHER",
            "PERLANCAR",
            "MANWAR",
            "FREW",
            "IVANWILLS",
            "BARBIE",
            "TOBYINK",
            "CJM",
            "MGV",
            "BOOK"
         ]
      }
   ]
}
