{
   "title" : {
      "text" : "CPAN Regulars Weekly (Top 10)"
   },
   "subtitle" : {
      "text" : "Last updated at 2016-08-28 04:00:01 GMT"
   },
   "series" : [
      {
         "meta" : [
            "ETHER",
            "PERLANCAR",
            "MANWAR",
            "MGV",
            "IVANWILLS",
            "EXODIST",
            "LEONT",
            "SYSPETE",
            "JONASS",
            "REEDFISH"
         ],
         "data" : [
            -234,
            -105,
            -104,
            -83,
            -32,
            -27,
            -9,
            -6,
            -6,
            -6
         ],
         "name" : "Current Chain"
      },
      {
         "meta" : [
            "ETHER",
            "FREW",
            "BARBIE",
            "TOBYINK",
            "CJM",
            "BOOK",
            "BINGOS",
            "RJBS",
            "PERLANCAR",
            "MANWAR"
         ],
         "data" : [
            234,
            200,
            165,
            133,
            132,
            129,
            125,
            122,
            105,
            104
         ],
         "name" : "Longest Chain"
      }
   ]
}
