{
   "subtitle" : {
      "text" : "Last updated at 2016-11-27 00:00:02 GMT"
   },
   "series" : [
      {
         "name" : "Current Chain",
         "data" : [
            -247,
            -118,
            -116,
            -96,
            -44,
            -19,
            -19,
            -17,
            -9,
            -9
         ],
         "meta" : [
            "ETHER",
            "PERLANCAR",
            "MANWAR",
            "MGV",
            "IVANWILLS",
            "JHTHORSEN",
            "REEDFISH",
            "DROLSKY",
            "BOOK",
            "HORNBURG"
         ]
      },
      {
         "name" : "Longest Chain",
         "meta" : [
            "ETHER",
            "FREW",
            "BARBIE",
            "TOBYINK",
            "CJM",
            "BOOK",
            "BINGOS",
            "RJBS",
            "PERLANCAR",
            "MANWAR"
         ],
         "data" : [
            247,
            200,
            165,
            133,
            132,
            129,
            125,
            122,
            118,
            116
         ]
      }
   ],
   "title" : {
      "text" : "CPAN Regulars Weekly (Top 10)"
   }
}
