{
   "series" : [
      {
         "meta" : [
            "ETHER",
            "PERLANCAR",
            "MANWAR",
            "MGV",
            "BOOK",
            "IVANWILLS",
            "EXODIST",
            "JJNAPIORK",
            "OALDERS",
            "RKELSCH"
         ],
         "name" : "Current Chain",
         "data" : [
            -230,
            -101,
            -99,
            -79,
            -28,
            -27,
            -23,
            -8,
            -8,
            -7
         ]
      },
      {
         "data" : [
            230,
            200,
            165,
            133,
            132,
            129,
            125,
            122,
            101,
            99
         ],
         "name" : "Longest Chain",
         "meta" : [
            "ETHER",
            "FREW",
            "BARBIE",
            "TOBYINK",
            "CJM",
            "BOOK",
            "BINGOS",
            "RJBS",
            "PERLANCAR",
            "MANWAR"
         ]
      }
   ],
   "subtitle" : {
      "text" : "Last updated at 2016-07-31 00:00:01 GMT"
   },
   "title" : {
      "text" : "CPAN Regulars Weekly (Top 10)"
   }
}
