{
   "subtitle" : {
      "text" : "Last updated at 2016-08-23 15:00:02 GMT"
   },
   "series" : [
      {
         "name" : "Current Chain",
         "data" : [
            -234,
            -105,
            -103,
            -82,
            -31,
            -27,
            -8,
            -6,
            -6,
            -6
         ],
         "meta" : [
            "ETHER",
            "PERLANCAR",
            "MANWAR",
            "MGV",
            "IVANWILLS",
            "EXODIST",
            "LEONT",
            "BIGPRESH",
            "SYSPETE",
            "JONASS"
         ]
      },
      {
         "data" : [
            234,
            200,
            165,
            133,
            132,
            129,
            125,
            122,
            105,
            103
         ],
         "meta" : [
            "ETHER",
            "FREW",
            "BARBIE",
            "TOBYINK",
            "CJM",
            "BOOK",
            "BINGOS",
            "RJBS",
            "PERLANCAR",
            "MANWAR"
         ],
         "name" : "Longest Chain"
      }
   ],
   "title" : {
      "text" : "CPAN Regulars Weekly (Top 10)"
   }
}
