{
   "title" : {
      "text" : "CPAN Regulars Weekly (Top 10)"
   },
   "series" : [
      {
         "meta" : [
            "ETHER",
            "PERLANCAR",
            "MANWAR",
            "MGV",
            "IVANWILLS",
            "ORANGE",
            "PREACTION",
            "WYANT",
            "SHLOMIF",
            "NEWELLC"
         ],
         "data" : [
            -250,
            -122,
            -120,
            -99,
            -47,
            -12,
            -11,
            -8,
            -8,
            -8
         ],
         "name" : "Current Chain"
      },
      {
         "name" : "Longest Chain",
         "data" : [
            250,
            200,
            165,
            133,
            132,
            129,
            125,
            122,
            122,
            120
         ],
         "meta" : [
            "ETHER",
            "FREW",
            "BARBIE",
            "TOBYINK",
            "CJM",
            "BOOK",
            "BINGOS",
            "RJBS",
            "PERLANCAR",
            "MANWAR"
         ]
      }
   ],
   "subtitle" : {
      "text" : "Last updated at 2016-12-20 14:30:01 GMT"
   }
}
