{
   "title" : {
      "text" : "CPAN Regulars Weekly (Top 10)"
   },
   "subtitle" : {
      "text" : "Last updated at 2017-02-12 08:30:02 GMT"
   },
   "series" : [
      {
         "data" : [
            -258,
            -130,
            -127,
            -107,
            -56,
            -13,
            -8,
            -7,
            -7,
            -7
         ],
         "meta" : [
            "ETHER",
            "PERLANCAR",
            "MANWAR",
            "MGV",
            "IVANWILLS",
            "BKB",
            "SRI",
            "KNTH",
            "PLICEASE",
            "OALDERS"
         ],
         "name" : "Current Chain"
      },
      {
         "name" : "Longest Chain",
         "meta" : [
            "ETHER",
            "FREW",
            "BARBIE",
            "TOBYINK",
            "CJM",
            "PERLANCAR",
            "BOOK",
            "MANWAR",
            "BINGOS",
            "RJBS"
         ],
         "data" : [
            258,
            200,
            165,
            133,
            132,
            130,
            129,
            127,
            125,
            122
         ]
      }
   ]
}
