{
   "series" : [
      {
         "data" : [
            -355,
            -226,
            -224,
            -152,
            -64,
            -10,
            -9,
            -6,
            -5,
            -5
         ],
         "meta" : [
            "ETHER",
            "PERLANCAR",
            "MANWAR",
            "IVANWILLS",
            "Perl6",
            "CORION",
            "KIMOTO",
            "JEFFOBER",
            "REEDFISH",
            "DBOOK"
         ],
         "name" : "Current Chain"
      },
      {
         "name" : "Longest Chain",
         "meta" : [
            "ETHER",
            "PERLANCAR",
            "MANWAR",
            "FREW",
            "BARBIE",
            "IVANWILLS",
            "TOBYINK",
            "CJM",
            "MGV",
            "BOOK"
         ],
         "data" : [
            355,
            226,
            224,
            200,
            165,
            152,
            133,
            132,
            130,
            129
         ]
      }
   ],
   "subtitle" : {
      "text" : "Last updated at 2018-12-23 00:00:02 GMT"
   },
   "title" : {
      "text" : "CPAN Regulars Weekly (Top 10)"
   }
}
