{
   "subtitle" : {
      "text" : "Last updated at 2017-07-17 06:00:02 GMT"
   },
   "series" : [
      {
         "name" : "Current Chain",
         "data" : [
            -280,
            -152,
            -150,
            -129,
            -77,
            -17,
            -12,
            -7,
            -5,
            -5
         ],
         "meta" : [
            "ETHER",
            "PERLANCAR",
            "MANWAR",
            "MGV",
            "IVANWILLS",
            "BINGOS",
            "DROLSKY",
            "PLICEASE",
            "OLIVER",
            "HOCHSTEN"
         ]
      },
      {
         "meta" : [
            "ETHER",
            "FREW",
            "BARBIE",
            "PERLANCAR",
            "MANWAR",
            "TOBYINK",
            "CJM",
            "MGV",
            "BOOK",
            "BINGOS"
         ],
         "data" : [
            280,
            200,
            165,
            152,
            150,
            133,
            132,
            129,
            129,
            125
         ],
         "name" : "Longest Chain"
      }
   ],
   "title" : {
      "text" : "CPAN Regulars Weekly (Top 10)"
   }
}
