{
   "subtitle" : {
      "text" : "Last updated at 2017-12-02 00:00:02 GMT"
   },
   "series" : [
      {
         "data" : [
            -300,
            -171,
            -169,
            -97,
            -26,
            -24,
            -18,
            -18,
            -9,
            -8
         ],
         "name" : "Current Chain",
         "meta" : [
            "ETHER",
            "PERLANCAR",
            "MANWAR",
            "IVANWILLS",
            "PLICEASE",
            "KIMOTO",
            "MGV",
            "PREACTION",
            "Perl6",
            "JACQUESG"
         ]
      },
      {
         "data" : [
            300,
            200,
            171,
            169,
            165,
            133,
            132,
            130,
            129,
            125
         ],
         "meta" : [
            "ETHER",
            "FREW",
            "PERLANCAR",
            "MANWAR",
            "BARBIE",
            "TOBYINK",
            "CJM",
            "MGV",
            "BOOK",
            "BINGOS"
         ],
         "name" : "Longest Chain"
      }
   ],
   "title" : {
      "text" : "CPAN Regulars Weekly (Top 10)"
   }
}
